<?xml version="1.0" encoding="UTF-8"?>
<objects serializationModel="Studio.01.10.00">
    <object class="AudioFile" id="{a997da65-2ce5-4074-8098-9ce93597f637}">
        <property name="assetPath">
            <value>SFX/disparoMuerte1.wav</value>
        </property>
        <property name="frequencyInKHz">
            <value>22.0499992</value>
        </property>
        <property name="channelCount">
            <value>1</value>
        </property>
        <property name="length">
            <value>5.1432199546485258</value>
        </property>
        <relationship name="masterAssetFolder">
            <destination>{a3dec2ad-2df2-4dd6-8baa-312f2925055e}</destination>
        </relationship>
    </object>
</objects>
