<?xml version="1.0" encoding="UTF-8"?>
<!--Arbol de comportamiento del pollito-->
<BehaviorTree>
    <Root id="1" type="selector">
        <Composition id="2" type="secuencia">
            <Leaf id="3" type="tarea" action="ve" target="jugador">
                <Blackboard task="escribe" info="pos-jugador"></Blackboard>
            </Leaf>
            <Leaf id="4" type="tarea" action="pide" target="ayuda">
                <Blackboard task="escribe" info="pos-ayuda"></Blackboard>
            </Leaf>
            <Decorator id="5" type="iterador" end="true">
                <Composition id="6" type="secuencia">   
                    <Leaf id="7" type="tarea" action="moverse" target="jugador"></Leaf>
                    <Leaf id="8" type="tarea" action="ataca" target="jugador"></Leaf>
                </Composition>
            </Decorator>
        </Composition>
        <Composition id="9" type="secuencia">   
            <Leaf id="10" type="tarea" action="oye" target="ayuda">
                <Blackboard task="lee" info="pos-ayuda"></Blackboard>
            </Leaf>
            <Leaf id="11" type="tarea" action="busca" target="pos-ayuda"></Leaf>
        </Composition>
        <Composition id="12" type="secuencia">
            <Leaf id="13" type="tarea" action="oye" target="jugador">
                <Blackboard task="escribe" info="pos-jugador"></Blackboard>
            </Leaf>
            <Leaf id="14" tarea="busca" target="pos-jugador">
                <Blackboard task="lee" info="pos-jugador"></Blackboard>
            </Leaf>
        </Composition>
        <Leaf id="15" type="tarea" action="merodea" target=""></Leaf>
    </Root>
</BehaviorTree>